{
	"parent": "minecraft:recipes/root",
	"rewards": {
		"recipes": [
			"wildlands:polished_gabbro_from_stonecutting",
			"wildlands:gabbro_wall_from_stonecutting",
			"wildlands:gabbro_slab_from_stonecutting",
			"wildlands:gabbro_stairs_from_stonecutting",
			"wildlands:polished_gabbro_slab_from_gabbro_stonecutting",
			"wildlands:polished_gabbro_stairs_from_gabbro_stonecutting"
		]
	},
	"criteria": {
		"has_item": {
			"trigger": "minecraft:inventory_changed",
			"conditions": {
				"items": [
					{
						"item": "wildlands:gabbro"
					}
				]
			}
		},
		"has_the_recipe": {
			"trigger": "minecraft:recipe_unlocked",
			"conditions": {
				"recipe": "wildlands:polished_gabbro_from_stonecutting"
			}
		}
	},
	"requirements": [
		[
			"has_item",
			"has_the_recipe"
		]
	]
}